matrix/__init__.py
matrix/matrix_admin.py
matrix/neo.py
matrix/client/__init__.py
matrix/client/request.py
matrix/client/server.py
matrix/manager/__init__.py
matrix/manager/admin.py
matrix/manager/build.py
matrix/manager/commit.py
matrix/manager/server.py
matrix/manager/test.py
matrix/templates/Dockerfile-oth
matrix/templates/Dockerfile-pt
matrix/templates/Dockerfile-tf
matrix/templates/__init__.py
matrix/templates/custom.zip
matrix/templates/pipeline_template.zip
matrix/utils/__init__.py
matrix/utils/auxiliary.py
matrix/utils/errors.py
matrix/utils/loaders.py
matrix/utils/logging.py
matrix/utils/versions.py
matrix_sdk-1.0.2.dist-info/METADATA
matrix_sdk-1.0.2.dist-info/WHEEL
matrix_sdk-1.0.2.dist-info/entry_points.txt
matrix_sdk-1.0.2.dist-info/top_level.txt
matrix_sdk-1.0.2.dist-info/RECORD
