Metadata-Version: 2.4
Name: matrix-sdk
Version: 1.0.2
Summary: A module to handle projects and connections to the Matrix repo server
Author: Matrix-AI Developers
Author-email: amirhosseinseddigh@gmail.com
Requires-Dist: setuptools
Requires-Dist: zipfile36>=0.1.3
Requires-Dist: requests>=2.31.0
Requires-Dist: tqdm>=4.66.2
Requires-Dist: importlib_metadata; python_version < "3.8"
Requires-Dist: packaging>=20.0
Requires-Dist: typing_extensions; python_version < "3.8"
Dynamic: author
Dynamic: author-email
Dynamic: requires-dist
Dynamic: summary
